nonebot_plugin_nezha/__init__.py
nonebot_plugin_nezha/api.py
nonebot_plugin_nezha/config.py
nonebot_plugin_nezha/depend.py
nonebot_plugin_nezha/model.py
nonebot_plugin_nezha/render.py
nonebot_plugin_nezha/tool.py
nonebot_plugin_nezha-0.5.1.dist-info/LICENSE
nonebot_plugin_nezha-0.5.1.dist-info/METADATA
nonebot_plugin_nezha-0.5.1.dist-info/WHEEL
nonebot_plugin_nezha-0.5.1.dist-info/RECORD
